rnaseq_lib
