Metadata-Version: 1.0
Name: rnaseq-lib
Version: 1.0a27
Summary: Library of convenience functions related to current research
Home-page: http://github.com/jvivian/rnaseq-lib
Author: John Vivian
Author-email: jtvivian@gmail.com
License: MIT
Platform: UNKNOWN
